pnu_vuxml-1.2.1.data/data/share/man/man1/vuxml.1.gz
pnu_vuxml-1.2.1.data/data/share/man/man3/vuxml.3.gz
vuxml/__init__.py
vuxml/library.py
vuxml/main.py
pnu_vuxml-1.2.1.dist-info/License
pnu_vuxml-1.2.1.dist-info/METADATA
pnu_vuxml-1.2.1.dist-info/WHEEL
pnu_vuxml-1.2.1.dist-info/entry_points.txt
pnu_vuxml-1.2.1.dist-info/top_level.txt
pnu_vuxml-1.2.1.dist-info/RECORD
